iToppy/__init__.py
iToppy/__version__.py
iToppy/exceptions.py
iToppy/models.py
iToppy-0.1.1.dist-info/LICENSE
iToppy-0.1.1.dist-info/METADATA
iToppy-0.1.1.dist-info/WHEEL
iToppy-0.1.1.dist-info/top_level.txt
iToppy-0.1.1.dist-info/zip-safe
iToppy-0.1.1.dist-info/RECORD
