Metadata-Version: 2.1
Name: iToppy
Version: 0.1.1
Summary: Python package for the iTop CMDB/Service Management Rest API
Home-page: https://github.com/scheiblingcopip3/iToppy
Author: Lars Scheibling
Author-email: lars@scheibling.se
License: GnuPG 3.0
Keywords: python itop itopy itoppy rest api cmdb service management
Classifier: Programming Language :: Python :: 3
Classifier: License :: OSI Approved :: GNU General Public License v3 (GPLv3)
Classifier: Operating System :: OS Independent
Requires-Python: >=3.6
License-File: LICENSE
Requires-Dist: requests
